{
  "project_info": {
    "project_number": "178797150389",
    "project_id": "alpha-stock-news-mobile-app",
    "storage_bucket": "alpha-stock-news-mobile-app.appspot.com"
  },
  "client": [
    {
      "client_info": {
        "mobilesdk_app_id": "1:178797150389:android:e846958f5e423393f17efc",
        "android_client_info": {
          "package_name": "com.alpha.stock_news_app_frontend"
        }
      },
      "oauth_client": [
        {
          "client_id": "178797150389-ai80o79ue1bvt4it364pq6f0iso6ok35.apps.googleusercontent.com",
          "client_type": 3
        }
      ],
      "api_key": [
        {
          "current_key": "AIzaSyDP0vMA6UuvNiskB-AN9NDa8bXvAs0bBks"
        }
      ],
      "services": {
        "appinvite_service": {
          "other_platform_oauth_client": [
            {
              "client_id": "178797150389-ai80o79ue1bvt4it364pq6f0iso6ok35.apps.googleusercontent.com",
              "client_type": 3
            },
            {
              "client_id": "178797150389-lv30t7nugkabikm5s9flr48bls802bsn.apps.googleusercontent.com",
              "client_type": 2,
              "ios_info": {
                "bundle_id": "com.example.stockNewsAppFrontend"
              }
            }
          ]
        }
      }
    },
    {
      "client_info": {
        "mobilesdk_app_id": "1:178797150389:android:bbee01d1a1a203fbf17efc",
        "android_client_info": {
          "package_name": "com.example.stock_news_app_frontend"
        }
      },
      "oauth_client": [
        {
          "client_id": "178797150389-0rv09ogkraovehpqa0sj96jlejotqdqd.apps.googleusercontent.com",
          "client_type": 1,
          "android_info": {
            "package_name": "com.example.stock_news_app_frontend",
            "certificate_hash": "a492e52e378cd49d3a1db6862227683624836944"
          }
        },
        {
          "client_id": "178797150389-ai80o79ue1bvt4it364pq6f0iso6ok35.apps.googleusercontent.com",
          "client_type": 3
        }
      ],
      "api_key": [
        {
          "current_key": "AIzaSyDP0vMA6UuvNiskB-AN9NDa8bXvAs0bBks"
        }
      ],
      "services": {
        "appinvite_service": {
          "other_platform_oauth_client": [
            {
              "client_id": "178797150389-ai80o79ue1bvt4it364pq6f0iso6ok35.apps.googleusercontent.com",
              "client_type": 3
            },
            {
              "client_id": "178797150389-lv30t7nugkabikm5s9flr48bls802bsn.apps.googleusercontent.com",
              "client_type": 2,
              "ios_info": {
                "bundle_id": "com.example.stockNewsAppFrontend"
              }
            }
          ]
        }
      }
    }
  ],
  "configuration_version": "1"
}